v2/crc_comb.v
module crc_comb #(
    parameter crc  = 32,
    parameter poly = 32'hEDB88320
) (
    input [crc-1:0] lfsr,
    input [3:0] data_reg,
    output [crc-1 : 0] lfsr_out
);

  wire t0, t1, t2, t3;
  wire [crc-1:0] d0, d1, d2, d3;



  assign t0 = data_reg[0] ^ lfsr[0];
  assign t1 = data_reg[1] ^ lfsr[1];
  assign t2 = data_reg[2] ^ lfsr[2];
  assign t3 = data_reg[3] ^ lfsr[3];


  assign d0 = poly & {crc{t0}};
  assign d1 = poly & {crc{t1}};
  assign d2 = poly & {crc{t2}};
  assign d3 = poly & {crc{t3}};

  assign lfsr_out = ({4'b0,lfsr[crc-1:4]}) ^ ({3'b0,d0[crc-1:3]}) ^ ({2'b0,d1[crc-1:2]}) ^ ({1'b0,d2[crc-1:1]}) ^ d3;







endmodule

v2/crc_top_v2.v

module crc_top_v2 #(
    parameter crc = 32,
    parameter poly = 32'hEDB88320,
    parameter n = 4,
    parameter residue = 32'h2144DF1C
) (
    input clk,
    input rst_n,
    input [n-1:0] data,
    input en_data,
    output reg correct
);

  wire [crc-1:0] lfsr_out;
  reg [n-1:0] data_reg;
  reg [crc-1:0] lfsr;
  reg en_lfsr;
  wire correct_wire;



  crc_comb #(
      .crc (crc),
      .poly(poly)
  ) uut (
      /*AUTOINST*/
      // Outputs
      .lfsr_out(lfsr_out[crc-1:0]),
      // Inputs
      .lfsr    (lfsr[crc-1:0]),
      .data_reg(data_reg[3:0])
  );


  // loading data.  rst not needed as initial does not matter
  always @(posedge clk) begin
    if (en_data) data_reg <= data;
  end


  //lfsr ff
  always @(posedge clk or negedge rst_n) begin
    if (~rst_n) lfsr <= {crc{1'b1}};
    else if (en_lfsr) lfsr <= lfsr_out;
  end

  // lfsr en ( 1 cycle delay after data loading  for the initial value(11111) of lfsr to undergo operation)

  always @(posedge clk or negedge rst_n) begin
    if (~rst_n) en_lfsr <= 0;
    else en_lfsr <= en_data;
  end

  // correct signal ff

  always @(posedge clk or negedge rst_n) begin
    if (~rst_n) correct <= 1'b0;
    else correct <= correct_wire;
  end


  assign correct_wire = (~lfsr == residue) ? 1'b1 : 1'b0;



endmodule

v2/crc_top_tb_v2.v
`timescale 1ns / 1ps


module crc_top_tb_v2;

  localparam crc = 32;
  localparam poly = 32'hEDB88320;
  localparam n = 4;
  localparam residue = 32'h2144DF1C;
  localparam data_size = 32;


  /*AUTOWIRE*/
  // Beginning of automatic wires (for undeclared instantiated-module outputs)
  wire correct;  // From uut of crc_top.v
  // End of automatics

  /*AUTOREGINPUT*/
  // Beginning of automatic reg inputs (for undeclared instantiated-module inputs)
  reg clk;  // To uut of crc_top.v
  reg [n-1:0] data;  // To uut of crc_top.v
  reg en_data;  // To uut of crc_top.v
  reg rst_n;  // To uut of crc_top.v
  // End of automatics

  reg [data_size-1:0] temp_reg = 32'h12345678;  // input 32 bit data



  reg [7:0] byte_reg;
  integer i;
  crc_top_v2 #(
      .crc(crc),
      .poly(poly),
      .n(n),
      .residue(residue)
  ) uut (

      /*AUTOINST*/
      // Outputs
      .correct(correct),
      // Inputs
      .clk    (clk),
      .rst_n  (rst_n),
      .data   (data[n-1:0]),
      .en_data(en_data)
  );

  initial begin
    clk = 0;
    forever #5 clk = ~clk;
  end

  initial begin
    $dumpfile("crc_top_tb_v2.vcd");
    $dumpvars(0, crc_top_tb_v2);

    rst_n   = 1;
    en_data = 0;
    #2 rst_n = 0;
    #2 rst_n = 1;

    @(negedge clk);
    en_data = 1;

    // byte sized data
    for (i = 0; i < (data_size / 8); i = i + 1) begin
      byte_reg = temp_reg[(data_size-1)-8*i-:8];
      data = byte_reg[3:0];
      @(negedge clk);
      data = byte_reg[7:4];
      @(negedge clk);
    end

    en_data = 0;
    repeat (2) @(posedge clk);  // en_lfsr to go low


    $display("lfsr= %h ", ~(uut.lfsr));

    #30 $finish;

  end

endmodule

v2/crc_top_tb_v2.vcd
$date
	Tue May 26 18:42:11 2026
$end
$version
	Icarus Verilog
$end
$timescale
	1ps
$end
$scope module crc_top_tb_v2 $end
$var wire 1 ! correct $end
$var parameter 32 " crc $end
$var parameter 32 # data_size $end
$var parameter 32 $ n $end
$var parameter 32 % poly $end
$var parameter 32 & residue $end
$var reg 8 ' byte_reg [7:0] $end
$var reg 1 ( clk $end
$var reg 4 ) data [3:0] $end
$var reg 1 * en_data $end
$var reg 1 + rst_n $end
$var reg 32 , temp_reg [31:0] $end
$var integer 32 - i [31:0] $end
$scope module uut $end
$var wire 1 ( clk $end
$var wire 4 . data [3:0] $end
$var wire 1 * en_data $end
$var wire 1 + rst_n $end
$var wire 32 / lfsr_out [31:0] $end
$var wire 1 0 correct_wire $end
$var parameter 32 1 crc $end
$var parameter 32 2 n $end
$var parameter 32 3 poly $end
$var parameter 32 4 residue $end
$var reg 1 ! correct $end
$var reg 4 5 data_reg [3:0] $end
$var reg 1 6 en_lfsr $end
$var reg 32 7 lfsr [31:0] $end
$scope module uut $end
$var wire 32 8 d0 [31:0] $end
$var wire 32 9 d1 [31:0] $end
$var wire 32 : d2 [31:0] $end
$var wire 32 ; d3 [31:0] $end
$var wire 4 < data_reg [3:0] $end
$var wire 32 = lfsr [31:0] $end
$var wire 32 > lfsr_out [31:0] $end
$var wire 1 ? t0 $end
$var wire 1 @ t1 $end
$var wire 1 A t2 $end
$var wire 1 B t3 $end
$var parameter 32 C crc $end
$var parameter 32 D poly $end
$upscope $end
$upscope $end
$upscope $end
$enddefinitions $end
$comment Show the parameter values. $end
$dumpall
b11101101101110001000001100100000 D
b100000 C
b100001010001001101111100011100 4
b11101101101110001000001100100000 3
b100 2
b100000 1
b100001010001001101111100011100 &
b11101101101110001000001100100000 %
b100 $
b100000 #
b100000 "
$end
#0
$dumpvars
xB
xA
x@
x?
bx >
bx =
bx <
bx0xx0xx0xxx000x00000xx00x00000 ;
bx0xx0xx0xxx000x00000xx00x00000 :
bx0xx0xx0xxx000x00000xx00x00000 9
bx0xx0xx0xxx000x00000xx00x00000 8
bx 7
x6
bx 5
x0
bx /
bx .
bx -
b10010001101000101011001111000 ,
1+
0*
bx )
0(
bx '
x!
$end
#2000
bx11xxxxxxxx11 /
bx11xxxxxxxx11 >
00
b11111111111111111111111111111111 7
b11111111111111111111111111111111 =
06
0!
0+
#4000
1+
#5000
1(
#10000
b10 )
b10 .
b10010 '
b0 -
1*
0(
#15000
b10001001001011000010110100101011 /
b10001001001011000010110100101011 >
b11101101101110001000001100100000 8
b0 9
b11101101101110001000001100100000 :
b11101101101110001000001100100000 ;
1?
0@
1A
1B
16
b10 5
b10 <
1(
#20000
b1 )
b1 .
0(
#25000
b11011110010001000110000100111010 /
b11011110010001000110000100111010 >
b0 :
b0 8
b11101101101110001000001100100000 9
0A
0?
1@
b10001001001011000010110100101011 7
b10001001001011000010110100101011 =
b1 5
b1 <
1(
#30000
b100 )
b100 .
b110100 '
b1 -
0(
#35000
b10101101111011101010010001101011 /
b10101101111011101010010001101011 >
b11101101101110001000001100100000 :
1A
b11011110010001000110000100111010 7
b11011110010001000110000100111010 =
b100 5
b100 <
1(
#40000
b11 )
b11 .
0(
#45000
b11100111011001100110100101100110 /
b11100111011001100110100101100110 >
b0 9
b0 :
0@
0A
b10101101111011101010010001101011 7
b10101101111011101010010001101011 =
b11 5
b11 <
1(
#50000
b110 )
b110 .
b1010110 '
b10 -
0(
#55000
b1110011101100110011010010110 /
b1110011101100110011010010110 >
b0 ;
0B
b11100111011001100110100101100110 7
b11100111011001100110100101100110 =
b110 5
b110 <
1(
#60000
b101 )
b101 .
0(
#65000
b100110001111100101011011000101 /
b100110001111100101011011000101 >
b11101101101110001000001100100000 8
b11101101101110001000001100100000 9
1?
1@
b1110011101100110011010010110 7
b1110011101100110011010010110 =
b101 5
b101 <
1(
#70000
b1000 )
b1000 .
b1111000 '
b11 -
0(
#75000
b10000100101100000011011110111000 /
b10000100101100000011011110111000 >
b0 9
b11101101101110001000001100100000 :
b11101101101110001000001100100000 ;
0@
1A
1B
b100110001111100101011011000101 7
b100110001111100101011011000101 =
b1000 5
b1000 <
1(
#80000
b111 )
b111 .
0(
#85000
b10110101111101101111000101100111 /
b10110101111101101111000101100111 >
b11101101101110001000001100100000 9
1@
b10000100101100000011011110111000 7
b10000100101100000011011110111000 =
b111 5
b111 <
1(
#90000
0*
b100 -
0(
#95000
b1011010111110110111100010110 /
b1011010111110110111100010110 >
b0 8
b0 9
b0 :
b0 ;
0?
0@
0A
0B
b10110101111101101111000101100111 7
b10110101111101101111000101100111 =
06
1(
